dm_core/__init__.py
dm_core/crypto/__init__.py
dm_core/crypto/asymmetric.py
dm_core/crypto/generate.py
dm_core/crypto/hasher.py
dm_core/crypto/symmetric.py
dm_core/crypto/management/commands/__init__.py
dm_core/crypto/management/commands/crypto.py
dm_core/crypto/tests/__init__.py
dm_core_crypto-1.0.1.dist-info/licenses/LICENSE
dm_core_crypto-1.0.1.dist-info/METADATA
dm_core_crypto-1.0.1.dist-info/WHEEL
dm_core_crypto-1.0.1.dist-info/top_level.txt
dm_core_crypto-1.0.1.dist-info/RECORD
